cvp/__init__.py
cvp/__main__.py
cvp/arguments.py
cvp/entrypoint.py
cvp/variables.py
cvp/aio/__init__.py
cvp/aio/policy.py
cvp/aio/run.py
cvp/aio/shield_any.py
cvp/apps/__init__.py
cvp/apps/player/__init__.py
cvp/apps/player/app.py
cvp/apps/worker/__init__.py
cvp/apps/worker/app.py
cvp/assets/__init__.py
cvp/assets/fonts/__init__.py
cvp/assets/fonts/JetBrainsMono/JetBrainsMonoNLNerdFontMono-Bold.ttf
cvp/assets/fonts/JetBrainsMono/JetBrainsMonoNLNerdFontMono-ExtraBold.ttf
cvp/assets/fonts/JetBrainsMono/JetBrainsMonoNLNerdFontMono-ExtraLight.ttf
cvp/assets/fonts/JetBrainsMono/JetBrainsMonoNLNerdFontMono-Light.ttf
cvp/assets/fonts/JetBrainsMono/JetBrainsMonoNLNerdFontMono-Medium.ttf
cvp/assets/fonts/JetBrainsMono/JetBrainsMonoNLNerdFontMono-Regular.ranges
cvp/assets/fonts/JetBrainsMono/JetBrainsMonoNLNerdFontMono-Regular.ttf
cvp/assets/fonts/JetBrainsMono/JetBrainsMonoNLNerdFontMono-SemiBold.ttf
cvp/assets/fonts/JetBrainsMono/JetBrainsMonoNLNerdFontMono-Thin.ttf
cvp/assets/fonts/JetBrainsMono/OFL.txt
cvp/assets/fonts/JetBrainsMono/README.md
cvp/assets/fonts/MaterialDesignIcons/LICENSE
cvp/assets/fonts/MaterialDesignIcons/materialdesignicons-webfont.glyphs
cvp/assets/fonts/MaterialDesignIcons/materialdesignicons-webfont.ranges
cvp/assets/fonts/MaterialDesignIcons/materialdesignicons-webfont.ttf
cvp/assets/fonts/NanumGothicCoding/NanumGothicCoding-Bold.ranges
cvp/assets/fonts/NanumGothicCoding/NanumGothicCoding-Bold.ttf
cvp/assets/fonts/NanumGothicCoding/NanumGothicCoding.ranges
cvp/assets/fonts/NanumGothicCoding/NanumGothicCoding.ttf
cvp/assets/fonts/NanumGothicCoding/OFL.md
cvp/assets/icons/__init__.py
cvp/assets/icons/icon.png
cvp/assets/wsdl/__init__.py
cvp/assets/wsdl/docs.oasis-open.org/wsn/b-2.xsd
cvp/assets/wsdl/docs.oasis-open.org/wsn/bw-2.wsdl
cvp/assets/wsdl/docs.oasis-open.org/wsn/t-1.xsd
cvp/assets/wsdl/docs.oasis-open.org/wsrf/bf-2.xsd
cvp/assets/wsdl/docs.oasis-open.org/wsrf/r-2.xsd
cvp/assets/wsdl/docs.oasis-open.org/wsrf/rw-2.wsdl
cvp-0.0.3.dist-info/LICENSE
cvp-0.0.3.dist-info/METADATA
cvp-0.0.3.dist-info/WHEEL
cvp-0.0.3.dist-info/entry_points.txt
cvp-0.0.3.dist-info/top_level.txt
cvp-0.0.3.dist-info/RECORD
