Metadata-Version: 2.1
Name: cvp
Version: 0.0.3
Summary: Computer Vision Player
Home-page: https://github.com/osom8979/cvp
Author: zer0
Author-email: osom8979@gmail.com
Maintainer: zer0
Maintainer-email: osom8979@gmail.com
License: MIT License
Project-URL: GitHub: issues, https://github.com/osom8979/cvp/issues
Project-URL: GitHub: repo, https://github.com/osom8979/cvp
Platform: UNKNOWN
Classifier: Development Status :: 4 - Beta
Classifier: Intended Audience :: Developers
Classifier: Intended Audience :: End Users/Desktop
Classifier: Intended Audience :: Information Technology
Classifier: Intended Audience :: Manufacturing
Classifier: Intended Audience :: Science/Research
Classifier: Operating System :: OS Independent
Classifier: Programming Language :: Python
Classifier: Programming Language :: Python :: 3.11
Classifier: Topic :: Multimedia
Classifier: Topic :: Multimedia :: Graphics
Classifier: Topic :: Multimedia :: Graphics :: 3D Rendering
Classifier: Topic :: Multimedia :: Graphics :: Viewers
Classifier: Topic :: Multimedia :: Video
Classifier: Topic :: Multimedia :: Video :: Capture
Classifier: Topic :: Multimedia :: Video :: Conversion
Classifier: Topic :: Multimedia :: Video :: Display
Classifier: Topic :: Multimedia :: Video :: Non-Linear Editor
Classifier: Topic :: Scientific/Engineering
Classifier: Topic :: Scientific/Engineering :: Artificial Intelligence
Classifier: Topic :: Scientific/Engineering :: Image Processing
Classifier: Topic :: Scientific/Engineering :: Image Recognition
Classifier: Topic :: Utilities
Requires-Python: >=3.11
License-File: LICENSE
Requires-Dist: PyOpenGL==3.1.7
Requires-Dist: PyOpenGL-accelerate==3.1.7
Requires-Dist: PyYAML==6.0.2
Requires-Dist: WSDiscovery==2.0.0
Requires-Dist: coloredlogs==15.0.1
Requires-Dist: cvlayer==0.32.0
Requires-Dist: fonttools==4.54.1
Requires-Dist: httpx==0.27.2
Requires-Dist: imgui==2.0.0
Requires-Dist: keyring==25.4.1
Requires-Dist: numpy==2.0.1
Requires-Dist: opencv-python-headless==4.10.0.84
Requires-Dist: orjson==3.10.6
Requires-Dist: plumbum==1.9.0
Requires-Dist: psutil==6.0.0
Requires-Dist: pygame-ce==2.4.1
Requires-Dist: pystray==0.19.5
Requires-Dist: python-dotenv==1.0.1
Requires-Dist: requests==2.32.3
Requires-Dist: sagecipher==0.7.5
Requires-Dist: shapely==2.0.6
Requires-Dist: type-serialize==1.3.0
Requires-Dist: uvloop==0.20.0
Requires-Dist: watchdog==5.0.0
Requires-Dist: zeep==4.2.1
